sroll_package/__init__.py
sroll_package/set_env.py
sroll_package/static/requirements.txt
sroll-0.2.9.9.dist-info/METADATA
sroll-0.2.9.9.dist-info/WHEEL
sroll-0.2.9.9.dist-info/top_level.txt
sroll-0.2.9.9.dist-info/RECORD
