Metadata-Version: 2.1
Name: sroll
Version: 0.2.9.9
Summary: Python package for SRoll installation
Home-page: https://gitlab.ifremer.fr/iaocea/srollex.git
Author: Theo Foulquier
Author-email: tfoulqui@ifremer.fr
License: BSD 2-clause
Platform: UNKNOWN
Classifier: Development Status :: 1 - Planning
Classifier: Intended Audience :: Science/Research
Classifier: License :: OSI Approved :: BSD License
Classifier: Operating System :: POSIX :: Linux
Classifier: Programming Language :: Python :: 3.6
Requires-Dist: virtualenv
Requires-Dist: numpy
Requires-Dist: art
